setup.cfg
setup.py
src/soaplib/__init__.py
src/soaplib.egg-info/PKG-INFO
src/soaplib.egg-info/SOURCES.txt
src/soaplib.egg-info/dependency_links.txt
src/soaplib.egg-info/namespace_packages.txt
src/soaplib.egg-info/not-zip-safe
src/soaplib.egg-info/requires.txt
src/soaplib.egg-info/top_level.txt
src/soaplib/core/__init__.py
src/soaplib/core/_base.py
src/soaplib/core/mime.py
src/soaplib/core/namespaces.py
src/soaplib/core/service.py
src/soaplib/core/styles.py
src/soaplib/core/wsdl.py
src/soaplib/core/zope2.py
src/soaplib/core/model/__init__.py
src/soaplib/core/model/base.py
src/soaplib/core/model/binary.py
src/soaplib/core/model/clazz.py
src/soaplib/core/model/enum.py
src/soaplib/core/model/exception.py
src/soaplib/core/model/primitive.py
src/soaplib/core/model/table.py
src/soaplib/core/server/__init__.py
src/soaplib/core/server/_base.py
src/soaplib/core/server/wsgi.py
src/soaplib/core/server/zeromq.py
src/soaplib/core/test/__init__.py
src/soaplib/core/test/test_service.py
src/soaplib/core/test/test_soap.py
src/soaplib/core/test/test_xml_output.py
src/soaplib/core/test/test_xsd_gen.py
src/soaplib/core/test/interop/__init__.py
src/soaplib/core/test/interop/test_suds.py
src/soaplib/core/test/interop/test_wsi.py
src/soaplib/core/test/interop/server/__init__.py
src/soaplib/core/test/interop/server/_service.py
src/soaplib/core/test/interop/server/http_basic.py
src/soaplib/core/test/interop/server/http_static.py
src/soaplib/core/test/interop/server/zeromq.py
src/soaplib/core/test/type/__init__.py
src/soaplib/core/test/type/test_binary.py
src/soaplib/core/test/type/test_clazz.py
src/soaplib/core/test/type/test_enum.py
src/soaplib/core/test/type/test_exception.py
src/soaplib/core/test/type/test_include.py
src/soaplib/core/test/type/test_primitive.py
src/soaplib/core/test/wsdl/__init__.py
src/soaplib/core/test/wsdl/defult_services.py
src/soaplib/core/test/wsdl/port_service_services.py
src/soaplib/core/test/wsdl/test_default_wsdl.py
src/soaplib/core/test/wsdl/test_wsdl_ports_services.py
src/soaplib/core/test/wsdl/wrappers.py
src/soaplib/core/util/__init__.py
src/soaplib/core/util/duration.py
src/soaplib/core/util/etreeconv.py
src/soaplib/core/util/model_utils.py
src/soaplib/core/util/odict.py
