Metadata-Version: 1.0
Name: soaplib
Version: 2.0.0-beta2
Summary: A transport and architecture agnostic soap (de)serialization library that focuses on making small, rpc-like messaging work.
Home-page: http://soaplib.github.com/soaplib/2_0/
Author: Chris Austin
Author-email: chris@sydneysys.com
License: LGPL
Keywords: soap,wsdl,wsgi
Platform: UNKNOWN
Classifier: Programming Language :: Python
Classifier: Operating System :: OS Independent
Classifier: Natural Language :: English
Classifier: Development Status :: 4 - Beta
Classifier: Intended Audience :: Developers
Classifier: Topic :: Internet :: WWW/HTTP :: Dynamic Content
